youtube_tools/__init__.py
youtube_tools/main.py
youtube_tools-0.0.0.dist-info/METADATA
youtube_tools-0.0.0.dist-info/WHEEL
youtube_tools-0.0.0.dist-info/entry_points.txt
youtube_tools-0.0.0.dist-info/RECORD
