Metadata-Version: 2.1
Name: youtube-tools
Version: 0.0.0
Summary: 
Author: Mischa van den Burg
Author-email: mischavandenburg@gmail.com
Requires-Python: >=3.12,<4.0
Classifier: Programming Language :: Python :: 3
Classifier: Programming Language :: Python :: 3.12
Requires-Dist: typer (>=0.12.5,<0.13.0)
Requires-Dist: youtube-transcript-api (>=0.6.2,<0.7.0)
